NginxDoc/README.md
NginxDoc/__init__.py
NginxDoc/__main__.py
NginxDoc/file.epub
NginxDoc/index.html
NginxDoc/css/__init__.py
NginxDoc/css/annotations.css
NginxDoc/css/main.css
NginxDoc/css/normalize.css
NginxDoc/css/popup.css
NginxDoc/font/__init__.py
NginxDoc/font/fontello.eot
NginxDoc/font/fontello.svg
NginxDoc/font/fontello.ttf
NginxDoc/font/fontello.woff
NginxDoc/img/__init__.py
NginxDoc/img/annotator-glyph-sprite.png
NginxDoc/img/annotator-icon-sprite.png
NginxDoc/img/apple-touch-icon.png
NginxDoc/img/cancelfullscreen.png
NginxDoc/img/close.png
NginxDoc/img/fullscreen.png
NginxDoc/img/loader.gif
NginxDoc/img/menu-icon.png
NginxDoc/img/save.png
NginxDoc/img/saved.png
NginxDoc/img/settings-s.png
NginxDoc/img/settings.png
NginxDoc/img/star.png
NginxDoc/js/__init__.py
NginxDoc/js/epub.js
NginxDoc/js/epub.min.js
NginxDoc/js/epub.min.map
NginxDoc/js/hooks.min.js
NginxDoc/js/hooks.min.map
NginxDoc/js/reader.js
NginxDoc/js/reader.js.map
NginxDoc/js/reader.min.js
NginxDoc/js/reader.min.map
NginxDoc/js/hooks/__init__.py
NginxDoc/js/hooks/extensions/__init__.py
NginxDoc/js/hooks/extensions/highlight.js
NginxDoc/js/libs/__init__.py
NginxDoc/js/libs/jquery.min.js
NginxDoc/js/libs/localforage.min.js
NginxDoc/js/libs/screenfull.js
NginxDoc/js/libs/screenfull.min.js
NginxDoc/js/libs/zip.min.js
NginxDoc/js/plugins/__init__.py
NginxDoc/js/plugins/hypothesis.js
NginxDoc/js/plugins/search.js
nginx_doc-2024.3.1.0.dist-info/METADATA
nginx_doc-2024.3.1.0.dist-info/WHEEL
nginx_doc-2024.3.1.0.dist-info/entry_points.txt
nginx_doc-2024.3.1.0.dist-info/top_level.txt
nginx_doc-2024.3.1.0.dist-info/RECORD
